[
    {
        "media": "聯合早報",
        "category": "国际",
        "timeText": "00:02",
        "time": "2026-06-24 00:02",
        "link": "https://www.zaobao.com.sg/news/world/story20260624-9253625",
        "title": "伊朗称将自主处置解冻资产",
        "seq": 1
    },
    {
        "media": "聯合早報",
        "category": "国际",
        "timeText": "00:10",
        "time": "2026-06-24 00:10",
        "link": "https://www.zaobao.com.sg/news/world/story20260624-9253641",
        "title": "哈梅内伊葬礼7月6日举行 德黑兰将放假三天",
        "seq": 2
    },
    {
        "media": "聯合早報",
        "category": "国际",
        "timeText": "00:18",
        "time": "2026-06-24 00:18",
        "link": "https://www.zaobao.com.sg/news/world/story20260624-9253657",
        "title": "美上诉法院裁定 特朗普政府可加速遣返移民",
        "seq": 3
    },
    {
        "media": "聯合早報",
        "category": "中国",
        "timeText": "05:00",
        "time": "2026-06-24 05:00",
        "link": "https://www.zaobao.com.sg/news/china/story20260624-9253379",
        "title": "庄慧良：需要《铁拳教育》支撑的“教权”危机",
        "seq": 4
    },
    {
        "media": "聯合早報",
        "category": "体育",
        "timeText": "06:00",
        "time": "2026-06-24 06:00",
        "link": "https://www.zaobao.com.sg/news/sports/story20260624-9250652",
        "title": "巴西收官战对阵苏格兰 内马尔是否上阵成焦点",
        "seq": 5
    },
    {
        "media": "聯合早報",
        "category": "体育",
        "timeText": "06:47",
        "time": "2026-06-24 06:47",
        "link": "https://www.zaobao.com.sg/news/sports/story20260624-9254071",
        "title": "葡萄牙5比0狂扫乌兹别克斯坦 帅罗献两球宣告王者归来",
        "seq": 6
    },
    {
        "media": "聯合早報",
        "category": "体育",
        "timeText": "06:53",
        "time": "2026-06-24 06:53",
        "link": "https://www.zaobao.com.sg/news/sports/story20260624-9254081",
        "title": "英格兰久攻不下加纳 痛失提前出线机会",
        "seq": 7
    },
    {
        "media": "聯合早報",
        "category": "中国",
        "timeText": "07:11",
        "time": "2026-06-24 07:11",
        "link": "https://www.zaobao.com.sg/news/china/story20260624-9254134",
        "title": "阿里巴巴起诉美国防部 寻求从涉军名单中移除",
        "seq": 8
    },
    {
        "media": "聯合早報",
        "category": "国际",
        "timeText": "07:12",
        "time": "2026-06-24 07:12",
        "link": "https://www.zaobao.com.sg/news/world/story20260624-9254091",
        "title": "国际海事组织宣布启动霍尔木兹海峡滞留海员疏散计划",
        "seq": 9
    },
    {
        "media": "聯合早報",
        "category": "国际",
        "timeText": "07:18",
        "time": "2026-06-24 07:18",
        "link": "https://www.zaobao.com.sg/news/world/story20260624-9254049",
        "title": "因全国范围内IT系统故障 德国全境铁路暂停运作",
        "seq": 10
    },
    {
        "media": "聯合早報",
        "category": "新加坡",
        "timeText": "07:21",
        "time": "2026-06-24 07:21",
        "link": "https://www.zaobao.com.sghttps://www.zaobao.com.sg/specials/the-audio-brief/20260624",
        "title": "听新闻：公务员可获0.45个月年中华红 | 金正恩强调要持续扩大核武力量",
        "seq": 11
    },
    {
        "media": "聯合早報",
        "category": "中国",
        "timeText": "07:45",
        "time": "2026-06-24 07:45",
        "link": "https://www.zaobao.com.sg/news/china/story20260624-9254146",
        "title": "中国深化涉麻精药品等成瘾性物质打击整治",
        "seq": 12
    },
    {
        "media": "聯合早報",
        "category": "国际",
        "timeText": "08:04",
        "time": "2026-06-24 08:04",
        "link": "https://www.zaobao.com.sg/news/world/story20260624-9254205",
        "title": "美国参议院通过决议 制衡特朗普发动战争权力",
        "seq": 13
    },
    {
        "media": "聯合早報",
        "category": "新加坡",
        "timeText": "08:06",
        "time": "2026-06-24 08:06",
        "link": "https://www.zaobao.com.sg/news/singapore/story20260624-9254222",
        "title": "全岛多处清早下大雨 一些路段或有淹水风险",
        "seq": 14
    },
    {
        "media": "聯合早報",
        "category": "体育",
        "timeText": "08:23",
        "time": "2026-06-24 08:23",
        "link": "https://www.zaobao.com.sg/news/sports/story20260624-9254249",
        "title": "法国主帅德尚母亲去世 将缺席球队对挪威重头戏",
        "seq": 15
    },
    {
        "media": "聯合早報",
        "category": "国际",
        "timeText": "08:28",
        "time": "2026-06-24 08:28",
        "link": "https://www.zaobao.com.sg/news/world/story20260624-9254276",
        "title": "崔贤号新型多用途驱逐舰正式进入朝鲜海军服役",
        "seq": 16
    },
    {
        "media": "聯合早報",
        "category": "中国",
        "timeText": "08:34",
        "time": "2026-06-24 08:34",
        "link": "https://www.zaobao.com.sg/news/china/story20260624-9254306",
        "title": "美媒：美商务部长私下称或对中国机器人采取行动",
        "seq": 17
    },
    {
        "media": "聯合早報",
        "category": "中国",
        "timeText": "08:34",
        "time": "2026-06-24 08:34",
        "link": "https://www.zaobao.com.sg/news/china/story20260624-9254306",
        "title": "美国据报审查中国机器人输美情况 或出台限制措施",
        "seq": 18
    },
    {
        "media": "聯合早報",
        "category": "中国",
        "timeText": "08:43",
        "time": "2026-06-24 08:43",
        "link": "https://www.zaobao.com.sg/news/china/story20260624-9254325",
        "title": "彭博：不满中国人身攻击 高市不愿在APEC期间与习近平会面",
        "seq": 19
    },
    {
        "media": "聯合早報",
        "category": "国际",
        "timeText": "08:44",
        "time": "2026-06-24 08:44",
        "link": "https://www.zaobao.com.sg/news/world/story20260624-9254322",
        "title": "巴方称伊美谅解备忘录谈判未涉弹道导弹议题",
        "seq": 20
    },
    {
        "media": "聯合早報",
        "category": "财经",
        "timeText": "08:48",
        "time": "2026-06-24 08:48",
        "link": "https://www.zaobao.com.sg/finance/singapore/story20260624-9253675",
        "title": "星期三可关注股票",
        "seq": 21
    },
    {
        "media": "聯合早報",
        "category": "体育",
        "timeText": "09:00",
        "time": "2026-06-24 09:00",
        "link": "https://www.zaobao.com.sg/news/sports/story20260624-9254365",
        "title": "因凡蒂诺：特朗普将出席世界杯决赛并颁奖",
        "seq": 22
    },
    {
        "media": "聯合早報",
        "category": "中国",
        "timeText": "09:06",
        "time": "2026-06-24 09:06",
        "link": "https://www.zaobao.com.sg/news/china/story20260624-9254407",
        "title": "辉瑞高管：中国超越欧洲 成为药物创新与研发重要力量",
        "seq": 23
    },
    {
        "media": "聯合早報",
        "category": "中国",
        "timeText": "09:07",
        "time": "2026-06-24 09:07",
        "link": "https://www.zaobao.com.sg/news/china/story20260624-9254410",
        "title": "中国全国人大常委会会议听取个别代表资格报告 审议任免案",
        "seq": 24
    },
    {
        "media": "聯合早報",
        "category": "体育",
        "timeText": "09:08",
        "time": "2026-06-24 09:08",
        "link": "https://www.zaobao.com.sg/news/sports/story20260624-9254391",
        "title": "一球力克巴拿马 克罗地亚保住出线希望",
        "seq": 25
    },
    {
        "media": "聯合早報",
        "category": "新加坡",
        "timeText": "09:09",
        "time": "2026-06-24 09:09",
        "link": "https://www.zaobao.com.sg/news/singapore/story20260624-9120083",
        "title": "不靠聚餐维系感情 坚守14年义工活动凝聚亲情",
        "seq": 26
    },
    {
        "media": "聯合早報",
        "category": "财经",
        "timeText": "09:12",
        "time": "2026-06-24 09:12",
        "link": "https://www.zaobao.com.sg/finance/singapore/story20260624-9254347",
        "title": "海指星期三开盘涨13.8点",
        "seq": 27
    },
    {
        "media": "聯合早報",
        "category": "财经",
        "timeText": "09:13",
        "time": "2026-06-24 09:13",
        "link": "https://www.zaobao.com.sg/finance/singapore/story20260624-9254369",
        "title": "星和总裁换人 副总裁威廉姆斯明年接任总裁",
        "seq": 28
    },
    {
        "media": "聯合早報",
        "category": "东南亚",
        "timeText": "12:52",
        "time": "2026-06-24 12:52",
        "link": "https://www.zaobao.com.sg/news/sea/story20260623-9249547",
        "title": "曼谷店屋遮雨棚坍塌夺一命 当局下令检查老旧建筑",
        "seq": 29
    },
    {
        "media": "聯合早報",
        "category": "体育",
        "timeText": "13:20",
        "time": "2026-06-24 13:20",
        "link": "https://www.zaobao.com.sg/news/sports/story20260623-9249747",
        "title": "世界杯上演阿拉伯德比 阿尔及利亚让一追二送约旦出局",
        "seq": 30
    },
    {
        "media": "聯合早報",
        "category": "体育",
        "timeText": "13:39",
        "time": "2026-06-24 13:39",
        "link": "https://www.zaobao.com.sg/news/sports/story20260623-9249895",
        "title": "“墨西哥吴镇宇”传奇奥乔亚 料在世界杯末轮小组赛守门",
        "seq": 31
    },
    {
        "media": "聯合早報",
        "category": "体育",
        "timeText": "14:00",
        "time": "2026-06-24 14:00",
        "link": "https://www.zaobao.com.sg/news/sports/story20260623-9245878",
        "title": "为出线也为面子 葡萄牙战乌兹别克斯坦非胜不可",
        "seq": 32
    },
    {
        "media": "聯合早報",
        "category": "体育",
        "timeText": "14:00",
        "time": "2026-06-24 14:00",
        "link": "https://www.zaobao.com.sg/news/sports/story20260623-9244789",
        "title": "英格兰加纳争世界杯L组头名 克罗地亚不容再失",
        "seq": 33
    },
    {
        "media": "聯合早報",
        "category": "东南亚",
        "timeText": "14:19",
        "time": "2026-06-24 14:19",
        "link": "https://www.zaobao.com.sg/news/sea/story20260623-9250036",
        "title": "美国提供四艘无人航行器 助菲监测水域应对威胁",
        "seq": 34
    },
    {
        "media": "聯合早報",
        "category": "东南亚",
        "timeText": "14:48",
        "time": "2026-06-24 14:48",
        "link": "https://www.zaobao.com.sg/news/sea/story20260623-9250335",
        "title": "森州宫廷风波升级 马国统治者会议罕见推迟",
        "seq": 35
    },
    {
        "media": "聯合早報",
        "category": "体育",
        "timeText": "15:01",
        "time": "2026-06-24 15:01",
        "link": "https://www.zaobao.com.sg/news/sports/story20260623-9250182",
        "title": "梅西姆巴佩哈兰德同日双响 世界杯金靴之争激烈",
        "seq": 36
    },
    {
        "media": "聯合早報",
        "category": "财经",
        "timeText": "15:40",
        "time": "2026-06-24 15:40",
        "link": "https://www.zaobao.com.sg/finance/singapore/story20260623-9249473",
        "title": "BMI：移动市场竞争激烈或掀整合潮 四家运营商降至三家",
        "seq": 37
    },
    {
        "media": "聯合早報",
        "category": "体育",
        "timeText": "16:25",
        "time": "2026-06-24 16:25",
        "link": "https://www.zaobao.com.sg/news/sports/story20260623-9251133",
        "title": "图赫尔：世界杯补水暂停 打断比赛势头",
        "seq": 38
    },
    {
        "media": "聯合早報",
        "category": "财经",
        "timeText": "16:35",
        "time": "2026-06-24 16:35",
        "link": "https://www.zaobao.com.sg/finance/world/story20260623-9251193",
        "title": "科技股获利回吐引发重挫 韩国股市星期二暴跌近10%",
        "seq": 39
    },
    {
        "media": "聯合早報",
        "category": "体育",
        "timeText": "16:40",
        "time": "2026-06-24 16:40",
        "link": "https://www.zaobao.com.sg/news/sports/story20260623-9251128",
        "title": "孙女花6000美元买世界杯门票落空 89岁爷爷场外崩溃痛哭",
        "seq": 40
    },
    {
        "media": "聯合早報",
        "category": "财经",
        "timeText": "16:55",
        "time": "2026-06-24 16:55",
        "link": "https://www.zaobao.com.sg/finance/world/story20260623-9251317",
        "title": "软银创始人孙正义不看好马斯克太空数据中心设想",
        "seq": 41
    },
    {
        "media": "聯合早報",
        "category": "东南亚",
        "timeText": "16:58",
        "time": "2026-06-24 16:58",
        "link": "https://www.zaobao.com.sg/news/sea/story20260623-9251507",
        "title": "买珍珠奶茶也能分期付款 泰国“先买后付”或让年轻人背更多债",
        "seq": 42
    },
    {
        "media": "聯合早報",
        "category": "财经",
        "timeText": "17:46",
        "time": "2026-06-24 17:46",
        "link": "https://www.zaobao.com.sg/finance/singapore/story20260623-9250696",
        "title": "评股论经：Info-Tech系统",
        "seq": 43
    },
    {
        "media": "聯合早報",
        "category": "财经",
        "timeText": "17:52",
        "time": "2026-06-24 17:52",
        "link": "https://www.zaobao.com.sg/finance/singapore/story20260623-9251854",
        "title": "科技股回吐亚股多收跌 海指一枝独秀微涨0.03%",
        "seq": 44
    },
    {
        "media": "聯合早報",
        "category": "中国",
        "timeText": "18:08",
        "time": "2026-06-24 18:08",
        "link": "https://www.zaobao.com.sg/news/china/story20260623-9251583",
        "title": "中国国产小客车将能当天买车当天上牌",
        "seq": 45
    },
    {
        "media": "聯合早報",
        "category": "国际",
        "timeText": "18:16",
        "time": "2026-06-24 18:16",
        "link": "https://www.zaobao.com.sg/news/world/story20260623-9251563",
        "title": "五眼联盟警告：AI加速网攻威胁  中俄等对手可在数月内突破西方网防",
        "seq": 46
    },
    {
        "media": "聯合早報",
        "category": "国际",
        "timeText": "18:22",
        "time": "2026-06-24 18:22",
        "link": "https://www.zaobao.com.sg/news/world/story20260623-9251737",
        "title": "乌克兰促安理会推动停火 称耐心并非无限",
        "seq": 47
    },
    {
        "media": "聯合早報",
        "category": "国际",
        "timeText": "18:28",
        "time": "2026-06-24 18:28",
        "link": "https://www.zaobao.com.sg/news/world/story20260623-9251967",
        "title": "维基百科不让AI直接参与内容编辑",
        "seq": 48
    },
    {
        "media": "聯合早報",
        "category": "中国",
        "timeText": "18:38",
        "time": "2026-06-24 18:38",
        "link": "https://www.zaobao.com.sg/news/china/story20260623-9252060",
        "title": "中国在全球最快超级电脑排行榜超越美国荣登榜首",
        "seq": 49
    },
    {
        "media": "聯合早報",
        "category": "新加坡",
        "timeText": "18:47",
        "time": "2026-06-24 18:47",
        "link": "https://www.zaobao.com.sg/news/singapore/story20260623-9252072",
        "title": "销售主管串谋行贿15万元 判监六个月又两周",
        "seq": 50
    },
    {
        "media": "聯合早報",
        "category": "东南亚",
        "timeText": "18:50",
        "time": "2026-06-24 18:50",
        "link": "https://www.zaobao.com.sg/news/sea/story20260623-9252198",
        "title": "【东谈西论】柔森州选：安华的大选压力测试？",
        "seq": 51
    },
    {
        "media": "聯合早報",
        "category": "新加坡",
        "timeText": "19:07",
        "time": "2026-06-24 19:07",
        "link": "https://www.zaobao.com.sg/news/singapore/story20260623-9251460",
        "title": "应对AI时代网络威胁 本地联手美企三年培训1500余人与机构",
        "seq": 52
    },
    {
        "media": "聯合早報",
        "category": "新加坡",
        "timeText": "19:14",
        "time": "2026-06-24 19:14",
        "link": "https://www.zaobao.com.sg/news/singapore/story20260623-9251722",
        "title": "【红蚂蚁】新加坡员工不敬业不开口？ 专家：未必是坏事",
        "seq": 53
    },
    {
        "media": "聯合早報",
        "category": "中国",
        "timeText": "19:25",
        "time": "2026-06-24 19:25",
        "link": "https://www.zaobao.com.sg/news/china/story20260623-9252620",
        "title": "王毅吁中俄推动金砖做强做大 成为全球南方第一方阵",
        "seq": 54
    },
    {
        "media": "聯合早報",
        "category": "东南亚",
        "timeText": "19:30",
        "time": "2026-06-24 19:30",
        "link": "https://www.zaobao.com.sg/news/sea/story20260623-9252552",
        "title": "柔南两港拟合计吞吐量 力求登上全球十大港口名单",
        "seq": 55
    },
    {
        "media": "聯合早報",
        "category": "财经",
        "timeText": "19:44",
        "time": "2026-06-24 19:44",
        "link": "https://www.zaobao.com.sg/finance/world/story20260623-9251808",
        "title": "周二美市盘前走低 聚焦甲骨文的裁员情况",
        "seq": 56
    },
    {
        "media": "聯合早報",
        "category": "东南亚",
        "timeText": "19:46",
        "time": "2026-06-24 19:46",
        "link": "https://www.zaobao.com.sg/news/sea/story20260623-9252159",
        "title": "人权组织：泰缅边境诈骗园区逾5000人仍被困",
        "seq": 57
    },
    {
        "media": "聯合早報",
        "category": "新加坡",
        "timeText": "19:53",
        "time": "2026-06-24 19:53",
        "link": "https://www.zaobao.com.sg/news/singapore/story20260623-9252604",
        "title": "Mercury Festival被指小型市集“抢客” 双方各执一词",
        "seq": 58
    },
    {
        "media": "聯合早報",
        "category": "中国",
        "timeText": "19:55",
        "time": "2026-06-24 19:55",
        "link": "https://www.zaobao.com.sg/news/china/story20260623-9252755",
        "title": "李强吁中韩拓展半导体人工智能等新兴产业合作",
        "seq": 59
    },
    {
        "media": "聯合早報",
        "category": "国际",
        "timeText": "19:57",
        "time": "2026-06-24 19:57",
        "link": "https://www.zaobao.com.sg/news/world/story20260623-9252515",
        "title": "欧洲热浪持续升级 法国录得史上最热夜晚",
        "seq": 60
    },
    {
        "media": "聯合早報",
        "category": "财经",
        "timeText": "19:57",
        "time": "2026-06-24 19:57",
        "link": "https://www.zaobao.com.sg/finance/singapore/story20260623-9131788",
        "title": "AI浪潮推动 台湾料连续两年成新加坡最大贸易伙伴",
        "seq": 61
    },
    {
        "media": "聯合早報",
        "category": "国际",
        "timeText": "20:05",
        "time": "2026-06-24 20:05",
        "link": "https://www.zaobao.com.sg/news/world/story20260623-9251897",
        "title": "金正恩要持续扩大核武力量  再称韩国为“最敌对国家”",
        "seq": 62
    },
    {
        "media": "聯合早報",
        "category": "中国",
        "timeText": "20:14",
        "time": "2026-06-24 20:14",
        "link": "https://www.zaobao.com.sg/news/china/story20260623-9251320",
        "title": "环太平洋军演前夕 中美西太平洋军事对垒态势升温",
        "seq": 63
    },
    {
        "media": "聯合早報",
        "category": "国际",
        "timeText": "20:16",
        "time": "2026-06-24 20:16",
        "link": "https://www.zaobao.com.sg/news/world/story20260623-9252084",
        "title": "美国暂时豁免石油制裁  伊朗否认同意恢复核检查",
        "seq": 64
    },
    {
        "media": "聯合早報",
        "category": "新加坡",
        "timeText": "20:29",
        "time": "2026-06-24 20:29",
        "link": "https://www.zaobao.com.sg/news/singapore/story20260623-9252355",
        "title": "2岁男童赤脚独自在马路玩 施救妇女叹路人袖手旁观",
        "seq": 65
    },
    {
        "media": "聯合早報",
        "category": "新加坡",
        "timeText": "20:39",
        "time": "2026-06-24 20:39",
        "link": "https://www.zaobao.com.sg/news/singapore/story20260623-9250773",
        "title": "陈杰豪：新加坡不急于立法 与业者合作实现AI治理",
        "seq": 66
    },
    {
        "media": "聯合早報",
        "category": "体育",
        "timeText": "20:39",
        "time": "2026-06-24 20:39",
        "link": "https://www.zaobao.com.sg/news/sports/story20260623-9252713",
        "title": "湖人球星八村垒来新：亚洲球员须改变“害羞”心态 勇于展现自我",
        "seq": 67
    },
    {
        "media": "聯合早報",
        "category": "中国",
        "timeText": "20:43",
        "time": "2026-06-24 20:43",
        "link": "https://www.zaobao.com.sg/news/china/story20260623-9252935",
        "title": "柬前首相洪森后天起访华与习近平李强会面",
        "seq": 68
    },
    {
        "media": "聯合早報",
        "category": "新加坡",
        "timeText": "20:58",
        "time": "2026-06-24 20:58",
        "link": "https://www.zaobao.com.sg/news/singapore/story20260623-9251786",
        "title": "陈振声：美国是否信誉大损 应留给历史评断",
        "seq": 69
    },
    {
        "media": "聯合早報",
        "category": "国际",
        "timeText": "21:19",
        "time": "2026-06-24 21:19",
        "link": "https://www.zaobao.com.sg/news/world/story20260623-9253048",
        "title": "以色列前总理承认曾向伊朗走私星链助示威者",
        "seq": 70
    },
    {
        "media": "聯合早報",
        "category": "国际",
        "timeText": "21:29",
        "time": "2026-06-24 21:29",
        "link": "https://www.zaobao.com.sg/news/world/story20260623-9253113",
        "title": "黎巴嫩称以士兵在南部枪杀两人",
        "seq": 71
    },
    {
        "media": "聯合早報",
        "category": "中国",
        "timeText": "21:42",
        "time": "2026-06-24 21:42",
        "link": "https://www.zaobao.com.sg/news/china/story20260623-9252316",
        "title": "美国在台协会处长：10年前两岸相互吸引已不存在",
        "seq": 72
    },
    {
        "media": "聯合早報",
        "category": "东南亚",
        "timeText": "21:50",
        "time": "2026-06-24 21:50",
        "link": "https://www.zaobao.com.sg/news/sea/story20260623-9253195",
        "title": "复制“世界杯球队”阵型 泰国要12年内跨越中等收入陷阱",
        "seq": 73
    },
    {
        "media": "聯合早報",
        "category": "新加坡",
        "timeText": "22:12",
        "time": "2026-06-24 22:12",
        "link": "https://www.zaobao.com.sg/news/singapore/story20260623-9252943",
        "title": "推广华语理事会：方言和华语不对立 人们没必要选边站",
        "seq": 74
    },
    {
        "media": "聯合早報",
        "category": "东南亚",
        "timeText": "22:13",
        "time": "2026-06-24 22:13",
        "link": "https://www.zaobao.com.sg/news/sea/story20260623-9252727",
        "title": "缓和紧张拼州选 伊党放行土团党柔州选沿用国盟标志",
        "seq": 75
    },
    {
        "media": "聯合早報",
        "category": "体育",
        "timeText": "22:16",
        "time": "2026-06-24 22:16",
        "link": "https://www.zaobao.com.sg/news/sports/story20260623-9253285",
        "title": "约旦球迷看世界杯直播酿踩踏事故 一死八伤",
        "seq": 76
    },
    {
        "media": "聯合早報",
        "category": "中国",
        "timeText": "22:31",
        "time": "2026-06-24 22:31",
        "link": "https://www.zaobao.com.sg/news/china/story20260623-9252132",
        "title": " “中国冲击论”卷土重来  欧洲警报频响对华重拳却难落下？",
        "seq": 77
    },
    {
        "media": "聯合早報",
        "category": "国际",
        "timeText": "22:37",
        "time": "2026-06-24 22:37",
        "link": "https://www.zaobao.com.sg/news/world/story20260623-9253383",
        "title": "伊朗和阿曼将研究霍尔木兹海峡服务收费问题",
        "seq": 78
    },
    {
        "media": "聯合早報",
        "category": "体育",
        "timeText": "22:39",
        "time": "2026-06-24 22:39",
        "link": "https://www.zaobao.com.sg/news/sports/story20260623-9253357",
        "title": "意大利国家队下课后重返意甲 加图索接掌拉齐奥兵符",
        "seq": 79
    },
    {
        "media": "聯合早報",
        "category": "国际",
        "timeText": "22:50",
        "time": "2026-06-24 22:50",
        "link": "https://www.zaobao.com.sg/news/world/story20260623-9253401",
        "title": "俄罗斯：美国并非乌克兰问题的“客观调解人”",
        "seq": 80
    },
    {
        "media": "聯合早報",
        "category": "新加坡",
        "timeText": "22:55",
        "time": "2026-06-24 22:55",
        "link": "https://www.zaobao.com.sg/news/singapore/story20260623-9253096",
        "title": "年轻律师留不住？法学院和律所：AI冲击与制度压力",
        "seq": 81
    },
    {
        "media": "聯合早報",
        "category": "中国",
        "timeText": "22:58",
        "time": "2026-06-24 22:58",
        "link": "https://www.zaobao.com.sg/news/china/story20260623-9253462",
        "title": "王毅在金砖会议强调加强战略性矿产资源合作",
        "seq": 82
    },
    {
        "media": "聯合早報",
        "category": "东南亚",
        "timeText": "23:01",
        "time": "2026-06-24 23:01",
        "link": "https://www.zaobao.com.sg/news/sea/story20260623-9253119",
        "title": "菲校园枪击案死伤增至23人 少年嫌凶或受网上暴力影响",
        "seq": 83
    },
    {
        "media": "聯合早報",
        "category": "财经",
        "timeText": "23:07",
        "time": "2026-06-24 23:07",
        "link": "https://www.zaobao.com.sg/finance/singapore/story20260623-9253218",
        "title": "日元兑美元逼近40年低位 兑新元接近历史低位",
        "seq": 84
    },
    {
        "media": "聯合早報",
        "category": "中国",
        "timeText": "23:21",
        "time": "2026-06-24 23:21",
        "link": "https://www.zaobao.com.sg/news/china/story20260623-9253544",
        "title": "台国防部公布福建舰再航经台湾海峡",
        "seq": 85
    },
    {
        "media": "聯合早報",
        "category": "财经",
        "timeText": "23:29",
        "time": "2026-06-24 23:29",
        "link": "https://www.zaobao.com.sg/finance/singapore/story20260623-9253561",
        "title": "新航发行15亿人民币点心债券 票息率2.38%",
        "seq": 86
    },
    {
        "media": "聯合早報",
        "category": "财经",
        "timeText": "23:57",
        "time": "2026-06-24 23:57",
        "link": "https://www.zaobao.com.sg/finance/singapore/story20260623-9253595",
        "title": "和美置地发行1.5亿元绿色债券 票息率3.3%",
        "seq": 87
    },
    {
        "media": "聯合早報",
        "category": "新加坡",
        "timeText": "23:58",
        "time": "2026-06-24 23:58",
        "link": "https://www.zaobao.com.sg/news/singapore/story20260623-9253636",
        "title": "涉太子集团案 新加坡警方调查两中国男子封逾6亿资产",
        "seq": 88
    },
    {
        "media": "聯合早報",
        "category": "新加坡",
        "timeText": "23:58",
        "time": "2026-06-24 23:58",
        "link": "https://www.zaobao.com.sg/news/singapore/story20260623-9253636",
        "title": "涉太子集团案 新加坡警方调查两中国男子封逾6亿元资产",
        "seq": 89
    }
]